nodimo/__init__.py
nodimo/_internal.py
nodimo/collection.py
nodimo/dimension.py
nodimo/groups.py
nodimo/matrix.py
nodimo/model.py
nodimo/power.py
nodimo/product.py
nodimo/py.typed
nodimo/quantity.py
nodimo/relation.py
nodimo-2.0.0.dist-info/LICENSE
nodimo-2.0.0.dist-info/METADATA
nodimo-2.0.0.dist-info/WHEEL
nodimo-2.0.0.dist-info/top_level.txt
nodimo-2.0.0.dist-info/RECORD
