Metadata-Version: 2.1
Name: nodimo
Version: 2.0.0
Summary: Nodimo is a tool that creates dimensionless models
Author-email: Rodrigo Castro <rodrigopcastro018@gmail.com>
Maintainer-email: Rodrigo Castro <rodrigopcastro018@gmail.com>
License: MIT License
Project-URL: Source, https://github.com/rodrigopcastro018/nodimo
Project-URL: Documentation, https://nodimo.readthedocs.io/
Keywords: dimensional analysis
Classifier: Development Status :: 5 - Production/Stable
Classifier: License :: OSI Approved :: MIT License
Classifier: Intended Audience :: Education
Classifier: Intended Audience :: Science/Research
Classifier: Topic :: Scientific/Engineering
Classifier: Programming Language :: Python
Classifier: Programming Language :: Python :: 3
Classifier: Programming Language :: Python :: 3.9
Classifier: Programming Language :: Python :: 3.10
Classifier: Programming Language :: Python :: 3.11
Classifier: Programming Language :: Python :: 3.12
Classifier: Programming Language :: Python :: 3 :: Only
Classifier: Typing :: Typed
Classifier: Operating System :: OS Independent
Requires-Python: >=3.9
License-File: LICENSE
Requires-Dist: sympy >=1.7
Provides-Extra: docs
Requires-Dist: sphinx >=7.2.6 ; extra == 'docs'
Requires-Dist: furo >=2024.1.29 ; extra == 'docs'
Requires-Dist: nbsphinx >=0.9.3 ; extra == 'docs'
Requires-Dist: numpydoc >=1.6.0 ; extra == 'docs'
Requires-Dist: IPython >=8.8.0 ; extra == 'docs'
Requires-Dist: sphinx-copybutton ; extra == 'docs'
Provides-Extra: format
Requires-Dist: black >=22.1.0 ; extra == 'format'
Provides-Extra: test
Requires-Dist: mypy >=1.0 ; extra == 'test'
Requires-Dist: pytest >=6.2 ; extra == 'test'
Requires-Dist: nbval >=0.11 ; extra == 'test'
Requires-Dist: coverage >=7.0 ; extra == 'test'
Requires-Dist: pytest-cov >=2.10 ; extra == 'test'
Provides-Extra: tox
Requires-Dist: tox >=4.0 ; extra == 'tox'
Requires-Dist: tox-pyenv-redux >=1.0 ; extra == 'tox'
